gateway_sdk/__cli__.py
gateway_sdk/__init__.py
gateway_sdk/bridge.py
gateway_sdk/factory.py
gateway_sdk/common/__init__.py
gateway_sdk/common/logging_config.py
gateway_sdk/common/tracing.py
gateway_sdk/protocols/__init__.py
gateway_sdk/protocols/message.py
gateway_sdk/protocols/protocol.py
gateway_sdk/protocols/a2a/gateway.py
gateway_sdk/protocols/acp/gateway.py
gateway_sdk/protocols/ap/gateway.py
gateway_sdk/protocols/mcp/gateway.py
gateway_sdk/transports/__init__.py
gateway_sdk/transports/transport.py
gateway_sdk/transports/nats/gateway.py
gateway_sdk/transports/slim/gateway.py
gateway_sdk/transports/streamable_http/gateway.py
gateway_sdk/transports/streamable_http/models.py
gateway_sdk-0.1.4.dist-info/METADATA
gateway_sdk-0.1.4.dist-info/WHEEL
gateway_sdk-0.1.4.dist-info/entry_points.txt
gateway_sdk-0.1.4.dist-info/licenses/LICENSE
gateway_sdk-0.1.4.dist-info/RECORD
