Metadata-Version: 2.4
Name: gateway-sdk
Version: 0.1.4
Author-email: Cody Hartsook <codyhartsook@gmail.com>
License-File: LICENSE
Requires-Python: ~=3.12
Requires-Dist: a2a-sdk==0.2.5
Requires-Dist: cisco-outshift-agent-utils<0.0.3,>=0.0.2
Requires-Dist: click>=8.2.0
Requires-Dist: coloredlogs<16,>=15.0.1
Requires-Dist: httpx>=0.28.1
Requires-Dist: langchain-community>=0.3.24
Requires-Dist: mcp[cli]>=1.10.1
Requires-Dist: nats-py<3,>=2.10.0
Requires-Dist: opentelemetry-instrumentation-starlette>=0.54b0
Requires-Dist: slim-bindings==0.3.6
Requires-Dist: traceloop-sdk>=0.40.5
Requires-Dist: uvicorn>=0.34.3
